mkdocs_git_snippet/__init__.py
mkdocs_git_snippet/plugin.py
mkdocs_git_snippet/util.py
mkdocs_git_snippet-0.1.2.dist-info/LICENSE
mkdocs_git_snippet-0.1.2.dist-info/METADATA
mkdocs_git_snippet-0.1.2.dist-info/WHEEL
mkdocs_git_snippet-0.1.2.dist-info/entry_points.txt
mkdocs_git_snippet-0.1.2.dist-info/top_level.txt
mkdocs_git_snippet-0.1.2.dist-info/RECORD
