Metadata-Version: 2.1
Name: mkdocs-git-snippet
Version: 0.1.2
Summary: An MkDocs plugin that reads snippets from Github Repositories.
Home-page: https://github.com/mercari/mkdocs-git-snippet
Author: Mercari
License: UNKNOWN
Platform: UNKNOWN
Requires-Python: >=3.5
License-File: LICENSE
Requires-Dist: mkdocs
Requires-Dist: pygithub (>=1.59.0)
Requires-Dist: parse
